poldecomp/__init__.py
poldecomp-0.0.2.dist-info/LICENSE.txt
poldecomp-0.0.2.dist-info/METADATA
poldecomp-0.0.2.dist-info/WHEEL
poldecomp-0.0.2.dist-info/top_level.txt
poldecomp-0.0.2.dist-info/RECORD
