Metadata-Version: 2.1
Name: poldecomp
Version: 0.0.2
Summary: This is poldecomp package
Home-page: https://github.com/raktim-ghosh
Author: Raktim Ghosh
Author-email: raktim.ghosh@ieee.org
License: UNKNOWN
Platform: UNKNOWN
Classifier: Programming Language :: Python :: 3
Classifier: License :: OSI Approved :: MIT License
Classifier: Operating System :: OS Independent
Requires-Python: >=3.6
